alchy/__init__.py
alchy/__pkg__.py
alchy/_compat.py
alchy/events.py
alchy/manager.py
alchy/model.py
alchy/query.py
alchy/search.py
alchy/session.py
alchy/types.py
alchy/utils.py
alchy-2.2.2.dist-info/DESCRIPTION.rst
alchy-2.2.2.dist-info/METADATA
alchy-2.2.2.dist-info/RECORD
alchy-2.2.2.dist-info/WHEEL
alchy-2.2.2.dist-info/metadata.json
alchy-2.2.2.dist-info/top_level.txt
