Metadata-Version: 2.0
Name: alchy
Version: 2.2.2
Summary: A SQLAlchemy extension for its declarative ORM that provides enhancements for model classes, queries, and sessions.
Home-page: https://github.com/dgilland/alchy
Author: Derrick Gilland
Author-email: dgilland@gmail.com
License: MIT License
Keywords: sqlalchemy databases orm declarative
Platform: UNKNOWN
Classifier: Development Status :: 5 - Production/Stable
Classifier: Environment :: Web Environment
Classifier: Intended Audience :: Developers
Classifier: Operating System :: OS Independent
Classifier: License :: OSI Approved :: MIT License
Classifier: Topic :: Database :: Front-Ends
Classifier: Topic :: Software Development :: Libraries :: Python Modules
Classifier: Programming Language :: Python
Classifier: Programming Language :: Python :: 2
Classifier: Programming Language :: Python :: 2.7
Classifier: Programming Language :: Python :: 3
Classifier: Programming Language :: Python :: 3.4
Classifier: Programming Language :: Python :: 3.5
Requires-Dist: SQLAlchemy (>=1.0.12)
Requires-Dist: pydash (>=3.4.7)
